steam_bday/__init__.py
steam_bday/config.py
steam_bday/main.py
steam_birthday-0.1.0.dist-info/METADATA
steam_birthday-0.1.0.dist-info/WHEEL
steam_birthday-0.1.0.dist-info/top_level.txt
steam_birthday-0.1.0.dist-info/RECORD
