Metadata-Version: 2.1
Name: steam-birthday
Version: 0.1.0
Summary: UNKNOWN
Home-page: https://github.com/Kymartin45/steamBirthday
Author: Kyle Martin
Author-email: kymartin4505@gmail.com
License: UNKNOWN
Platform: UNKNOWN
